pep508_parser/__init__.py
pep508_parser/grammar.py
pep508_parser/parser.py
pep508_parser-2019.3.dist-info/COPYING
pep508_parser-2019.3.dist-info/METADATA
pep508_parser-2019.3.dist-info/WHEEL
pep508_parser-2019.3.dist-info/entry_points.txt
pep508_parser-2019.3.dist-info/top_level.txt
pep508_parser-2019.3.dist-info/RECORD
