Metadata-Version: 2.1
Name: pep508-parser
Version: 2019.3
Summary: A parser for the PEP508 dependency specification.
Home-page: https://github.com/NFJones/pep508-parser
Author: Neil F Jones
License: UNKNOWN
Keywords: pep508
Platform: UNKNOWN
Classifier: Intended Audience :: Developers
Classifier: Topic :: Software Development :: Build Tools
Classifier: License :: OSI Approved :: MIT License
Classifier: Programming Language :: Python :: 3
Requires-Python: !=3.0.*, !=3.1.*, !=3.2.*, !=3.3.*, <4
Requires-Dist: Parsley (==1.3)
